mcp_servers123456_demo/__init__.py
mcp_servers123456_demo/py.typed
mcp_servers123456_demo/test.py
mcp_servers123456_demo-0.1.14.dist-info/METADATA
mcp_servers123456_demo-0.1.14.dist-info/WHEEL
mcp_servers123456_demo-0.1.14.dist-info/entry_points.txt
mcp_servers123456_demo-0.1.14.dist-info/RECORD
