Metadata-Version: 2.4
Name: mcp-servers123456-demo
Version: 0.1.14
Summary: Add your description here
Requires-Python: >=3.12
Requires-Dist: mcp[cli]>=1.10.1
